pythonjsonlogger/__init__.py
pythonjsonlogger/core.py
pythonjsonlogger/defaults.py
pythonjsonlogger/json.py
pythonjsonlogger/msgspec.py
pythonjsonlogger/orjson.py
pythonjsonlogger/py.typed
python_json_logger-3.1.0.dist-info/LICENSE
python_json_logger-3.1.0.dist-info/METADATA
python_json_logger-3.1.0.dist-info/NOTICE
python_json_logger-3.1.0.dist-info/WHEEL
python_json_logger-3.1.0.dist-info/top_level.txt
python_json_logger-3.1.0.dist-info/RECORD
