Metadata-Version: 2.1
Name: python-json-logger
Version: 3.1.0
Summary: JSON Log Formatter for the Python Logging Package
Author-email: Zakaria Zajac <zak@madzak.com>, Nicholas Hairs <info+python-json-logger@nicholashairs.com>
Maintainer-email: Nicholas Hairs <info+python-json-logger@nicholashairs.com>
License: BSD-2-Clause License
Project-URL: Homepage, https://nhairs.github.io/python-json-logger/latest/
Project-URL: GitHub, https://github.com/nhairs/python-json-logger
Classifier: Development Status :: 6 - Mature
Classifier: Intended Audience :: Developers
Classifier: License :: OSI Approved :: BSD License
Classifier: Operating System :: OS Independent
Classifier: Programming Language :: Python :: 3 :: Only
Classifier: Programming Language :: Python :: 3.8
Classifier: Programming Language :: Python :: 3.9
Classifier: Programming Language :: Python :: 3.10
Classifier: Programming Language :: Python :: 3.11
Classifier: Programming Language :: Python :: 3.12
Classifier: Topic :: System :: Logging
Classifier: Typing :: Typed
Requires-Python: >=3.8
License-File: LICENSE
License-File: NOTICE
Requires-Dist: typing-extensions
Provides-Extra: dev
Requires-Dist: validate-pyproject[all] ; extra == 'dev'
Requires-Dist: black ; extra == 'dev'
Requires-Dist: pylint ; extra == 'dev'
Requires-Dist: mypy ; extra == 'dev'
Requires-Dist: pytest ; extra == 'dev'
Requires-Dist: freezegun ; extra == 'dev'
Requires-Dist: tzdata ; extra == 'dev'
Requires-Dist: build ; extra == 'dev'
Requires-Dist: mkdocs ; extra == 'dev'
Requires-Dist: mkdocs-material >=8.5 ; extra == 'dev'
Requires-Dist: mkdocs-awesome-pages-plugin ; extra == 'dev'
Requires-Dist: mdx-truly-sane-lists ; extra == 'dev'
Requires-Dist: mkdocstrings[python] ; extra == 'dev'
Requires-Dist: mkdocs-gen-files ; extra == 'dev'
Requires-Dist: mkdocs-literate-nav ; extra == 'dev'
Requires-Dist: mike ; extra == 'dev'
Requires-Dist: orjson ; (implementation_name != "pypy" and python_version < "3.13") and extra == 'dev'
Requires-Dist: msgspec ; (implementation_name != "pypy" and python_version < "3.13") and extra == 'dev'
Requires-Dist: backports.zoneinfo ; (python_version < "3.9") and extra == 'dev'
